{
  "bioproject_id": "PRJNA687229",
  "articles": [
    {
      "title": "Trachymyrmex septentrionalis ant microbiome assembly is unique to individual colonies and castes",
      "link": "https://journals.asm.org/doi/abs/10.1128/msphere.00989-21",
      "citations": 14,
      "bioproject_id": "PRJNA687229",
      "doi": "10.1128/msphere"
    },
    {
      "title": "The Characterization of the Microbiome and Mollicute Symbionts in Fungus-Growing Ant T. Septentrionalis and Four North American Fireflies",
      "link": "https://search.proquest.com/openview/d8e211cf19d59e27b47676ec43fb9be3/1?pq-origsite=gscholar&cbl=18750&diss=y",
      "citations": 0,
      "bioproject_id": "PRJNA687229"
    }
  ],
  "total_articles": 2,
  "scrape_timestamp": "2025-09-03T13:43:26.436317",
  "runs": 6
}